tysins/ __main__.py
tysins/__init__.py
tysins/android_transfer.py
tysins/main.py
tysins-0.1.0.dist-info/licenses/LICENSE
tysins-0.1.0.dist-info/METADATA
tysins-0.1.0.dist-info/WHEEL
tysins-0.1.0.dist-info/entry_points.txt
tysins-0.1.0.dist-info/top_level.txt
tysins-0.1.0.dist-info/RECORD
