Metadata-Version: 2.4
Name: tysins
Version: 0.1.0
Summary: Android transfer CLI tool
Author: Ervuln
Classifier: Programming Language :: Python :: 3
Classifier: License :: OSI Approved :: MIT License
Requires-Python: >=3.6
License-File: LICENSE
Dynamic: author
Dynamic: classifier
Dynamic: description-content-type
Dynamic: license-file
Dynamic: requires-python
Dynamic: summary
